BetterText/BetterText.py
BetterText/__init__.py
BetterText-1.0.6.dist-info/LICENSE
BetterText-1.0.6.dist-info/METADATA
BetterText-1.0.6.dist-info/WHEEL
BetterText-1.0.6.dist-info/top_level.txt
BetterText-1.0.6.dist-info/RECORD
